vecrec/__init__.py
vecrec/collisions.py
vecrec/shapes.py
vecrec-0.3.1.dist-info/LICENSE.txt
vecrec-0.3.1.dist-info/WHEEL
vecrec-0.3.1.dist-info/METADATA
vecrec-0.3.1.dist-info/RECORD
