Metadata-Version: 1.1
Name: vecrec
Version: 0.3.1
Summary: 2D vector and rectangle classes.
Home-page: https://github.com/kxgames/vecrec
Author: Kale Kundert
Author-email: kale@thekunderts.net
